sof4raway_url_downloader/__init__.py
sof4raway_url_downloader/download.py
sof4raway_url_downloader-0.0.3.dist-info/LICENSE.txt
sof4raway_url_downloader-0.0.3.dist-info/METADATA
sof4raway_url_downloader-0.0.3.dist-info/WHEEL
sof4raway_url_downloader-0.0.3.dist-info/top_level.txt
sof4raway_url_downloader-0.0.3.dist-info/RECORD
