Metadata-Version: 2.1
Name: sof4raway_url_downloader
Version: 0.0.3
Summary: A Custom Library for Downloading Files from URLs
Home-page: https://github.com/sof4raway
Author: Muhammad Farid Rahman
Keywords: URL Downloader
Classifier: Development Status :: 5 - Production/Stable
Classifier: Intended Audience :: Education
Classifier: Operating System :: OS Independent
Classifier: License :: OSI Approved :: MIT License
Classifier: Programming Language :: Python :: 3
Classifier: Programming Language :: Python :: 3.10
Requires-Python: >=3.10
License-File: LICENSE.txt
Requires-Dist: requests
Requires-Dist: tqdm
